jubi/__init__.py
jubi/abc.py
jubi/core.py
jubi/utils.py
jubi/contrib/__init__.py
jubi/contrib/aiohttp.py
jubi-0.1.0.dist-info/DESCRIPTION.rst
jubi-0.1.0.dist-info/METADATA
jubi-0.1.0.dist-info/RECORD
jubi-0.1.0.dist-info/WHEEL
jubi-0.1.0.dist-info/metadata.json
jubi-0.1.0.dist-info/top_level.txt
